counterProject/counter.v
module counterBasis (
    input Clock,
    input Reset,
    input Enable,
    input Load,
    input upOrDown,
    input [3:0] in,
    output reg [3:0] out
);

always @(posedge Clock or posedge Reset) begin //clock signal or reset
        if (Reset) begin
            out <= 4'b0000;  // set counter to 0
        end 
        else if (Enable) begin 
            if (Load) begin
                out <= in;
            end 
            else if (upOrDown) begin
                out <= out + 1'b1;
            end 
            else begin
                out <= out - 1'b1;
            end
        end
    end

endmodule

counterProject/testbench.v
`timescale 1ns/1ps

module tb_counter;

    reg Clock;
    reg Reset;
    reg Enable;
    reg Load;
    reg upOrDown;
    reg [3:0] in;
    wire [3:0] out;

    // call counter.v module
    counterBasis asd (
        .Clock(Clock),
        .Reset(Reset),
        .Enable(Enable),
        .Load(Load),
        .upOrDown(upOrDown),
        .in(in),
        .out(out)
    );

    // Clock CYcles
    initial begin
        Clock = 0;
        forever #5 Clock = ~Clock;  // Her 5ns'de sinyali değiştir
    end
    
    //test the code
    initial begin
        $dumpfile("testbench.vcd");
        $dumpvars(0, tb_counter);
        // #10 = 1 clock cycle

        // Start
        Reset = 1; Enable = 0; Load = 0; upOrDown = 1; in = 4'b0000;
        #15 Reset = 0; Enable = 1; // Activates the system
        
        // Up Counting
        #30;
        
        // Reset
        Reset = 1;
        #10;
        Reset = 0;
        
        // Up Counting again
        #50;
        
        // Down Counting
        upOrDown = 0; 
        #40;
        
        // Load Value
        in = 4'b1010; // Input the value of 10
        Load = 1;
        #10 Load = 0;
        
        // OVerflow
        upOrDown = 1; // Up Counting again
        #80;          // Go over 15
        
        $finish;
    end

endmodule

counterProject/testbench.vcd
$date
	Sun May 03 22:53:01 2026
$end
$version
	Icarus Verilog
$end
$timescale
	1ps
$end
$scope module tb_counter $end
$var wire 4 ! out [3:0] $end
$var reg 1 " Clock $end
$var reg 1 # Enable $end
$var reg 1 $ Load $end
$var reg 1 % Reset $end
$var reg 4 & in [3:0] $end
$var reg 1 ' upOrDown $end
$scope module asd $end
$var wire 1 " Clock $end
$var wire 1 # Enable $end
$var wire 1 $ Load $end
$var wire 1 % Reset $end
$var wire 4 ( in [3:0] $end
$var wire 1 ' upOrDown $end
$var reg 4 ) out [3:0] $end
$upscope $end
$upscope $end
$enddefinitions $end
$comment Show the parameter values. $end
$dumpall
$end
#0
$dumpvars
b0 )
b0 (
1'
b0 &
1%
0$
0#
0"
b0 !
$end
#5000
1"
#10000
0"
#15000
b1 !
b1 )
1"
1#
0%
#20000
0"
#25000
b10 !
b10 )
1"
#30000
0"
#35000
b11 !
b11 )
1"
#40000
0"
#45000
b0 !
b0 )
1"
1%
#50000
0"
#55000
b1 !
b1 )
1"
0%
#60000
0"
#65000
b10 !
b10 )
1"
#70000
0"
#75000
b11 !
b11 )
1"
#80000
0"
#85000
b100 !
b100 )
1"
#90000
0"
#95000
b101 !
b101 )
1"
#100000
0"
#105000
b100 !
b100 )
1"
0'
#110000
0"
#115000
b11 !
b11 )
1"
#120000
0"
#125000
b10 !
b10 )
1"
#130000
0"
#135000
b1 !
b1 )
1"
#140000
0"
#145000
b1010 !
b1010 )
1"
1$
b1010 &
b1010 (
#150000
0"
#155000
b1011 !
b1011 )
1"
1'
0$
#160000
0"
#165000
b1100 !
b1100 )
1"
#170000
0"
#175000
b1101 !
b1101 )
1"
#180000
0"
#185000
b1110 !
b1110 )
1"
#190000
0"
#195000
b1111 !
b1111 )
1"
#200000
0"
#205000
b0 !
b0 )
1"
#210000
0"
#215000
b1 !
b1 )
1"
#220000
0"
#225000
b10 !
b10 )
1"
#230000
0"
#235000
b11 !
b11 )
1"
